start.py
app/__init__.py
app/main.py
app/api/__init__.py
app/api/advanced_reports.py
app/api/endpoints.py
app/core/__init__.py
app/core/config.py
app/models/__init__.py
app/models/report.py
app/services/__init__.py
app/services/report_generator-sync.py
app/services/report_generator.py
app/utils/__init__.py
app/utils/exa_search.py
tests/__init__.py
tests/test_main.py
tests/test_report_generator.py
agentic_reports-0.1.5.dist-info/LICENSE
agentic_reports-0.1.5.dist-info/METADATA
agentic_reports-0.1.5.dist-info/WHEEL
agentic_reports-0.1.5.dist-info/entry_points.txt
agentic_reports-0.1.5.dist-info/top_level.txt
agentic_reports-0.1.5.dist-info/RECORD
