Metadata-Version: 2.1
Name: agentic-reports
Version: 0.1.5
Summary: Agent Reporting using Exa.ai API.
Home-page: https://github.com/ruvnet/agentic-reports
Author: rUv
Author-email: null@ruv.net
License: Apache License 2.0
Classifier: Development Status :: 3 - Alpha
Classifier: Intended Audience :: Developers
Classifier: Topic :: Software Development :: Libraries :: Application Frameworks
Classifier: License :: OSI Approved :: Apache Software License
Classifier: Programming Language :: Python :: 3
Classifier: Programming Language :: Python :: 3.10
Requires-Python: >=3.10
License-File: LICENSE
Requires-Dist: twine
Requires-Dist: setuptools
Requires-Dist: wheel
Requires-Dist: flake8
Requires-Dist: black
Requires-Dist: pytest
Requires-Dist: pip-upgrader
Requires-Dist: fastapi
Requires-Dist: uvicorn
Requires-Dist: pandas
Requires-Dist: pydantic
Requires-Dist: exa-py
Requires-Dist: pydantic-settings
Requires-Dist: virtualenv
Requires-Dist: litellm
